alotofeffort/__init__.py
alotofeffort/main.py
alotofeffort/send.py
alotofeffort-0.4.1.dist-info/DESCRIPTION.rst
alotofeffort-0.4.1.dist-info/entry_points.txt
alotofeffort-0.4.1.dist-info/METADATA
alotofeffort-0.4.1.dist-info/metadata.json
alotofeffort-0.4.1.dist-info/RECORD
alotofeffort-0.4.1.dist-info/top_level.txt
alotofeffort-0.4.1.dist-info/WHEEL
