Metadata-Version: 2.0
Name: alotofeffort
Version: 0.4.1
Summary: Deploy static HTML sites to S3 at the command line.
Home-page: https://github.com/audreyr/alotofeffort
Author: Audrey Roy
Author-email: audreyr@gmail.com
License: BSD
Keywords: alotofeffort
Platform: UNKNOWN
Classifier: Development Status :: 2 - Pre-Alpha
Classifier: Intended Audience :: Developers
Classifier: License :: OSI Approved :: BSD License
Classifier: Natural Language :: English
Classifier: Programming Language :: Python :: 2
Classifier: Programming Language :: Python :: 2.6
Classifier: Programming Language :: Python :: 2.7
Requires-Dist: boto (==2.38.0)
